{"DnaSha":"\uFFFD\uFFFDv\u028A?|N\uFFFD\uFFFD[k\u0001\uFFFD3V\u0623\u001DM","dnaSha":"\uFFFD\uFFFDv\u028A?|N\uFFFD\uFFFD[k\u0001\uFFFD3V\u0623\u001DM","Categories":[{"CategoryName":"Skin","SelectionKey":0,"TintIndex":5,"XOffset":0.0,"YOffset":0.0},{"CategoryName":"Mouth","SelectionKey":1018,"TintIndex":0,"XOffset":0.0,"YOffset":0.0},{"CategoryName":"Nose","SelectionKey":2018,"TintIndex":0,"XOffset":0.0,"YOffset":0.0},{"CategoryName":"Eyes","SelectionKey":3018,"TintIndex":2,"XOffset":0.0,"YOffset":0.0},{"CategoryName":"Brow","SelectionKey":4018,"TintIndex":0,"XOffset":0.0,"YOffset":0.0},{"CategoryName":"Accessory","SelectionKey":5000,"TintIndex":1,"XOffset":0.0,"YOffset":0.0},{"CategoryName":"Hair","SelectionKey":6018,"TintIndex":16,"XOffset":0.0,"YOffset":0.0},{"CategoryName":"Glow","SelectionKey":7000,"TintIndex":0,"XOffset":0.0,"YOffset":0.0}]}